django_bookmark/admin.py
django_bookmark/apps.py
django_bookmark/migrations/0001_initial.py
django_bookmark/migrations/__init__.py
django_bookmark/models.py
django_bookmark/templates/django_bookmark/bookmark_list.html
django_bookmark/templates/django_bookmark/toggle_bookmark.html
django_bookmark/templatetags/django_bookmark.py
django_bookmark/urls.py
django_bookmark/views.py
django_bookmark-0.1.0.dist-info/LICENSE
django_bookmark-0.1.0.dist-info/METADATA
django_bookmark-0.1.0.dist-info/WHEEL
django_bookmark-0.1.0.dist-info/RECORD
